middlewares/__init__.py
middlewares/middlewares.py
middlewares/py.typed
fastapi_middlewares-0.2.0.dist-info/METADATA
fastapi_middlewares-0.2.0.dist-info/WHEEL
fastapi_middlewares-0.2.0.dist-info/licenses/LICENSE
fastapi_middlewares-0.2.0.dist-info/RECORD
