Metadata-Version: 2.4
Name: fastapi-middlewares
Version: 0.2.0
Summary: Essential middlewares for FastAPI
Project-URL: Homepage, https://github.com/mahdijafaridev/fastapi-middlewares
Project-URL: Repository, https://github.com/mahdijafaridev/fastapi-middlewares
Project-URL: Issues, https://github.com/mahdijafaridev/fastapi-middlewares/issues
Project-URL: Documentation, https://github.com/mahdijafaridev/fastapi-middlewares#readme
Project-URL: Changelog, https://github.com/mahdijafaridev/fastapi-middlewares/blob/main/CHANGELOG.md
Author-email: Mahdi Jafari <mahdijafaridev@gmail.com>
Maintainer-email: Mahdi Jafari <mahdijafaridev@gmail.com>
License: MIT
License-File: LICENSE
Keywords: asgi,fastapi,logging,middleware,monitoring,security,starlette
Classifier: Development Status :: 4 - Beta
Classifier: Framework :: AsyncIO
Classifier: Framework :: FastAPI
Classifier: Intended Audience :: Developers
Classifier: License :: OSI Approved :: MIT License
Classifier: Operating System :: OS Independent
Classifier: Programming Language :: Python :: 3
Classifier: Programming Language :: Python :: 3.10
Classifier: Programming Language :: Python :: 3.11
Classifier: Programming Language :: Python :: 3.12
Classifier: Topic :: Internet :: WWW/HTTP :: HTTP Servers
Classifier: Topic :: Internet :: WWW/HTTP :: WSGI :: Middleware
Classifier: Topic :: Software Development :: Libraries :: Python Modules
Classifier: Typing :: Typed
Requires-Python: >=3.10
Requires-Dist: bandit>=1.9.2
Requires-Dist: build>=1.3.0
Requires-Dist: fastapi>=0.121.0
Requires-Dist: starlette>=0.50.0
Requires-Dist: twine>=6.2.0
